farl/__init__.py
farl/base.py
farl/constants.py
farl/decorators.py
farl/dependencies.py
farl/exceptions.py
farl/handlers.py
farl/manager.py
farl/middleware.py
farl/openapi.py
farl/py.typed
farl/types.py
farl-0.0.8.dist-info/METADATA
farl-0.0.8.dist-info/WHEEL
farl-0.0.8.dist-info/RECORD
