Metadata-Version: 2.4
Name: farl
Version: 0.0.8
Summary: A FastAPI rate limiting library.
Author-email: nafnix <uwu@nafnix.com>
Requires-Python: >=3.11
Requires-Dist: fastapi>=0.116.1
Requires-Dist: limits>=5.4.0
Provides-Extra: redis
Requires-Dist: redis[hiredis]>=6.4.0; extra == 'redis'
